Workbook

Sheet README
A1: Section 7, pass 2: verification sheet
A3: Every row is one value from the second, page-referenced reading of the 71 empirical studies (reasons for data, learners and measures; model-selection criterion and data; test methodology cited; evidence beyond classifier scores; explicit or implied selection of settings on evaluation data).
A4: How to use: open the PDF at the page in column G, compare with the quote in column F, then set column I (yellow) to verified, corrected or wrong. Put the corrected value and the page in column K.
A5: Column H shows the independent spot check already done on 20 claims (confirmed / partly). Partly confirmed claims were narrowed in the text.
A6: Sheet citations: OpenAlex counts used for the citation ratios, retrieved 2026-10-18. Sheet summary: counts by status, recalculated from the codes sheet.
A7: Example of a filled row: status = verified, checked_by = Tan, note = "quote matches p. 7".
A8: Generated from the Section 7 coded data; regenerate rather than edit the coded values by hand.

Sheet codes
A1: key | B1: study | C1: year | D1: field | E1: coded value | F1: quote (verbatim, max 30 words) | G1: where in the paper | H1: spot check | I1: status | J1: checked_by | K1: correction / note
A2: OSS-1997 | B2: OSS | C2: 1997 | D2: data: reasons | E2: application_domain, imbalance_level, public_benchmark | F2: experimented with some data files from the UCI repository (Murphy and Aha, 1994) so that other researchers can replicate the experiments and double-check our results. | G2: pdf p. 5, Sec. 4.1 (also pdf p. 2, Sec. 1)
A3: OSS-1997 | B3: OSS | C3: 1997 | D3: data: access | E3: all public=False; source per dataset=True; links=False; modified data released=False | G3: pdf p. 5, Sec. 4.1 and Table 3; pdf p. 7, Acknowledgements
A4: OSS-1997 | B4: OSS | C4: 1997 | D4: learners: reasons | E4: popular | F4: In particular, 1-NN and C4.5 were selected because of their widespread use and well-known performance. | G4: pdf p. 5, Sec. 4.1
A5: OSS-1997 | B5: OSS | C5: 1997 | D5: model selection | E5: selected: not stated | criterion: not stated | data: not stated
A6: OSS-1997 | B6: OSS | C6: 1997 | D6: measures: reasons | E6: accuracy_misleading, cost, other | F6: As pointed out by many authors, the classifier's performance in applications of this kind cannot be expressed in terms of the average accuracy | G6: pdf p. 1, Sec. 1; pdf p. 2, Sec. 2.1
A7: OSS-1997 | B7: OSS | C7: 1997 | D7: tests: methodology cited | E7: none
A8: OSS-1997 | B8: OSS | C8: 1997 | D8: beyond classifier scores | E8: other | Tables 4-7 report the number of training examples kept after each selection step (S, C, T) next to a+, a-, g and acc. Figs. 2-4 are schematic drawings of borderline, noisy and redundant negatives, not plots of data. | G8: pdf p. 6, Tables 4-7; pdf pp. 3-4, Figs. 2-4
A9: SHRINK-1998 | B9: SHRINK | C9: 1998 | D9: data: reasons | E9: application_domain | F9: In this paper we describe an application of machine learning to an important environmental problem: detection of oil spills from radar images of the sea surface. | G9: p. 195, Sec. 1; p. 206, Sec. 6 (images deliberately acquired to contain slicks) | H9: partly
A10: SHRINK-1998 | B10: SHRINK | C10: 1998 | D10: data: access | E10: all public=False; source per dataset=True; links=False; modified data released=False | G10: p. 204, Sec. 6; p. 205, Table 2 | H10: partly
A11: SHRINK-1998 | B11: SHRINK | C11: 1998 | D11: learners: reasons | E11: none stated | H11: partly
A12: SHRINK-1998 | B12: SHRINK | C12: 1998 | D12: model selection | E12: selected: best variant | criterion: G-mean | data: evaluation data | F12: Unfortunately, we had too little oil spill data to hold any out for final system testing in the development phase of the project. | G12: p. 203, Sec. 5 (g-mean as feedback on design decisions); p. 205, Sec. 6 (no held-out data) | H12: partly
A13: SHRINK-1998 | B13: SHRINK | C13: 1998 | D13: measures: reasons | E13: accuracy_misleading, threshold_free, minority_focus, cost | F13: This measure would have to address the clear inadequacy of accuracy, which is unuseable in our problem. To this end, we have mainly used the geometric mean | G13: pp. 201-203, Sec. 5 | H13: partly
A14: SHRINK-1998 | B14: SHRINK | C14: 1998 | D14: tests: methodology cited | E14: none | G14: p. 208, Sec. 7 (t-test on one-sided selection results, Table 3) | H14: partly
A15: SHRINK-1998 | B15: SHRINK | C15: 1998 | D15: beyond classifier scores | E15: none | H15: partly
A16: SHRINK-1998 | B16: SHRINK | C16: 1998 | D16: settings chosen on evaluation data | E16: explicit | F16: Unfortunately, we had too little oil spill data to hold any out for final system testing in the development phase of the project. | G16: p. 203, Sec. 5 (g-mean as feedback on design decisions); p. 205, Sec. 6 (no held-out data) | H16: partly
A17: SMOTE-2002 | B17: SMOTE | C17: 2002 | D17: data: reasons | E17: varied_characteristics | F17: These datasets vary extensively in their size and class proportions, thus offering different domains for SMOTE. | G17: p. 333, Sec. 5.1 (also p. 352, Sec. 7: 'varying degrees of imbalance ... diverse testbed')
A18: SMOTE-2002 | B18: SMOTE | C18: 2002 | D18: data: access | E18: all public=False; source per dataset=True; links=True; modified data released=False | G18: pp. 328-334, Sec. 5.1, footnotes 1, 3, 4; Table 2
A19: SMOTE-2002 | B19: SMOTE | C19: 2002 | D19: learners: reasons | E19: other | F19: These different learning algorithms allowed SMOTE to be compared to some methods that can handle misclassification costs directly. | G19: p. 332, Sec. 5
A20: SMOTE-2002 | B20: SMOTE | C20: 2002 | D20: model selection | E20: selected: sampling rate | criterion: not stated | data: evaluation data | F20: We only show the best results from SMOTE combined with under-sampling and the plain under-sampling curve in the graphs. | G20: p. 335, Sec. 5.2
A21: SMOTE-2002 | B21: SMOTE | C21: 2002 | D21: measures: reasons | E21: accuracy_misleading, threshold_free, standard_in_literature, cost | F21: Area Under the ROC Curve (AUC) is a useful metric for classifier performance as it is independent of the decision criterion selected and prior probabilities. | G21: p. 322, Sec. 1; p. 323, Sec. 2
A22: SMOTE-2002 | B22: SMOTE | C22: 2002 | D22: tests: methodology cited | E22: none
A23: SMOTE-2002 | B23: SMOTE | C23: 2002 | D23: beyond classifier scores | E23: toy_2d_visualization, other | Fig. 3 plots decision regions on a 2-attribute, 10% subset of Mammography for replication vs synthetic over-sampling; Fig. 4 compares C4.5 tree sizes | G23: pp. 327-330, Figs. 3-4, Sec. 4.1-4.2
A24: SMOTE-2002 | B24: SMOTE | C24: 2002 | D24: settings chosen on evaluation data | E24: explicit | F24: We only show the best results from SMOTE combined with under-sampling and the plain under-sampling curve in the graphs. | G24: p. 335, Sec. 5.2
A25: SMOTEBoost-2003 | B25: SMOTEBoost | C25: 2003 | D25: data: reasons | E25: varied_characteristics | F25: Data sets used in our experiments contained different degrees of imbalance and different sizes, thus providing a diverse test bed. | G25: p. 117, Sec. 5 (Conclusions)
A26: SMOTEBoost-2003 | B26: SMOTEBoost | C26: 2003 | D26: data: access | E26: all public=None; source per dataset=True; links=True; modified data released=False | G26: p. 112, Sec. 4 and Table 2; refs [1], [20]-[24] p. 118-119
A27: SMOTEBoost-2003 | B27: SMOTEBoost | C27: 2003 | D27: learners: reasons | E27: none stated
A28: SMOTEBoost-2003 | B28: SMOTEBoost | C28: 2003 | D28: model selection | E28: selected: sampling rate | criterion: F1 | data: evaluation data | F28: Tables 3 to 6 include the precision, recall, and F-value for the various methods at different amounts of SMOTE (best values are given in bold). | G28: p. 115, Sec. 4; Tables 3-6
A29: SMOTEBoost-2003 | B29: SMOTEBoost | C29: 2003 | D29: measures: reasons | E29: accuracy_misleading, minority_focus, standard_in_literature | F29: for domains with imbalanced and/or skewed distributions, classification accuracy is not sufficient as a standard performance measure. | G29: p. 108, Sec. 1
A30: SMOTEBoost-2003 | B30: SMOTEBoost | C30: 2003 | D30: tests: methodology cited | E30: none
A31: SMOTEBoost-2003 | B31: SMOTEBoost | C31: 2003 | D31: beyond classifier scores | E31: none
A32: SMOTEBoost-2003 | B32: SMOTEBoost | C32: 2003 | D32: settings chosen on evaluation data | E32: explicit | F32: Tables 3 to 6 include the precision, recall, and F-value for the various methods at different amounts of SMOTE (best values are given in bold). | G32: p. 115, Sec. 4; Tables 3-6
A33: SMOTE-ENN-Tomek-2004 | B33: Batista et al. | C33: 2004 | D33: data: reasons | E33: varied_characteristics | F33: we have selected thirteen data sets from UCI [3] which have different degrees of imbalance. | G33: p. 24, Sec. 5
A34: SMOTE-ENN-Tomek-2004 | B34: Batista et al. | C34: 2004 | D34: data: access | E34: all public=True; source per dataset=True; links=True; modified data released=False | G34: p. 24, Sec. 5; p. 25, Table 3; p. 29, Ref. [3] (UCI URL)
A35: SMOTE-ENN-Tomek-2004 | B35: Batista et al. | C35: 2004 | D35: learners: reasons | E35: none stated
A36: SMOTE-ENN-Tomek-2004 | B36: Batista et al. | C36: 2004 | D36: model selection | E36: selected: none (fixed settings) | criterion: not applicable | data: not applicable | F36: We decided to add/remove examples until a balanced distribution was reached. | G36: p. 25, Sec. 5
A37: SMOTE-ENN-Tomek-2004 | B37: Batista et al. | C37: 2004 | D37: measures: reasons | E37: accuracy_misleading, threshold_free, cost | F37: Error rate and accuracy are particularly suspicious performance measures when studying the effect of class distribution on learning since they are strongly biased to favor the majority class. | G37: pp. 21-22, Sec. 3
A38: SMOTE-ENN-Tomek-2004 | B38: Batista et al. | C38: 2004 | D38: tests: methodology cited | E38: none | G38: p. 26, Sec. 5 (Hsu's MCB test, 95%); p. 27, Tables 6-7
A39: SMOTE-ENN-Tomek-2004 | B39: Batista et al. | C39: 2004 | D39: beyond classifier scores | E39: other | Tables 8-9 and Figs. 6-7 compare number of induced rules and conditions per rule for original vs Random over-sampling, Smote, Smote+Tomek, Smote+ENN (unpruned C4.5). | G39: p. 26, Sec. 5; p. 28, Tables 8-9, Figs. 6-7
A40: Borderline-SMOTE-2005 | B40: Borderline-SMOTE | C40: 2005 | D40: data: reasons | E40: none stated
A41: Borderline-SMOTE-2005 | B41: Borderline-SMOTE | C41: 2005 | D41: data: access | E41: all public=True; source per dataset=True; links=True; modified data released=False | G41: p. 883, Sec. 4, Table 2; p. 887, Ref. [24]
A42: Borderline-SMOTE-2005 | B42: Borderline-SMOTE | C42: 2005 | D42: learners: reasons | E42: none stated
A43: Borderline-SMOTE-2005 | B43: Borderline-SMOTE | C43: 2005 | D43: model selection | E43: selected: none (fixed settings) | criterion: not applicable | data: not applicable | F43: the value of m in our methods is set in a way that, the number of the minority examples in DANGER is about half of the minority class. | G43: p. 884, Sec. 4
A44: Borderline-SMOTE-2005 | B44: Borderline-SMOTE | C44: 2005 | D44: measures: reasons | E44: accuracy_misleading, minority_focus, standard_in_literature | F44: Since the nature of imbalance problem is to improve the prediction performance of the minority class, we only present the results of the minority class. | G44: p. 884, Sec. 4; p. 879-880, Sec. 2.1
A45: Borderline-SMOTE-2005 | B45: Borderline-SMOTE | C45: 2005 | D45: tests: methodology cited | E45: none
A46: Borderline-SMOTE-2005 | B46: Borderline-SMOTE | C46: 2005 | D46: beyond classifier scores | E46: toy_2d_visualization | Fig. 1 shows the simulated 2-D Circle data: original points, detected borderline minority examples, and the borderline synthetic examples generated | G46: p. 883, Sec. 3, Fig. 1
A47: Cluster-SMOTE-2006 | B47: Cluster-SMOTE | C47: 2006 | D47: data: reasons | E47: application_domain, varied_characteristics, other | F47: We chose to construct our own “real-world” intrusion dataset by tapping the Notre Dame traffic to avoid the various limitations of the DARPA traffic [8]. | G47: p. 1, Sec. I; p. 2, Sec. II
A48: Cluster-SMOTE-2006 | B48: Cluster-SMOTE | C48: 2006 | D48: data: access | E48: all public=False; source per dataset=True; links=False; modified data released=False | G48: p. 2, Sec. II and II-A/II-B, Table I
A49: Cluster-SMOTE-2006 | B49: Cluster-SMOTE | C49: 2006 | D49: learners: reasons | E49: simplicity, other | F49: While this application is used heavily in many, text-driven data-mining experiments, its noise tolerance makes it very useful in many other studies, such as our own. | G49: p. 3, Sec. III-A
A50: Cluster-SMOTE-2006 | B50: Cluster-SMOTE | C50: 2006 | D50: model selection | E50: selected: sampling rate | criterion: other: visual ROC-curve dominance / ROC convex hull | data: evaluation data | F50: Another deviation is that the best ROC curve for replication was at 100% level, indicating that more replication led to severe overfitting. | G50: p. 4, Fig. 3 caption ('optimal SMOTE'); p. 5, Sec. V-A (Fig. 4 'best results') and Sec. V-B
A51: Cluster-SMOTE-2006 | B51: Cluster-SMOTE | C51: 2006 | D51: measures: reasons | E51: cost, other | F51: Receiver Operating Characteristic (ROC) Curves provide an effective basis for comparison between classifiers of imbalanced datasets by tracing the increase in the rate of false alarms | G51: p. 4, Sec. IV-A; p. 3, Sec. III
A52: Cluster-SMOTE-2006 | B52: Cluster-SMOTE | C52: 2006 | D52: tests: methodology cited | E52: none
A53: Cluster-SMOTE-2006 | B53: Cluster-SMOTE | C53: 2006 | D53: beyond classifier scores | E53: none
A54: Cluster-SMOTE-2006 | B54: Cluster-SMOTE | C54: 2006 | D54: settings chosen on evaluation data | E54: explicit | F54: Another deviation is that the best ROC curve for replication was at 100% level, indicating that more replication led to severe overfitting. | G54: p. 4, Fig. 3 caption ('optimal SMOTE'); p. 5, Sec. V-A (Fig. 4 'best results') and Sec. V-B
A55: Global-CS-2006 | B55: Global-CS | C55: 2006 | D55: data: reasons | E55: none stated
A56: Global-CS-2006 | B56: Global-CS | C56: 2006 | D56: data: access | E56: all public=True; source per dataset=True; links=True; modified data released=None | G56: p. 570, Experiments, Table 2 and text ('14 UCI data sets ... and 6 synthetic data sets'); p. 572, References (Blake, Keogh & Merz 1998, repository URL)
A57: Global-CS-2006 | B57: Global-CS | C57: 2006 | D57: learners: reasons | E57: matches_mechanism | F57: Since C4.5 decision tree can deal with weighted examples, it is used as the cost-blind learner (denoted by BLIND) in the experiments. | G57: p. 569, Experiments
A58: Global-CS-2006 | B58: Global-CS | C58: 2006 | D58: model selection | E58: selected: none (fixed settings) | criterion: not applicable | data: not applicable | G58: pp. 569-571, Experiments (weights computed from the cost matrix; no tuning described)
A59: Global-CS-2006 | B59: Global-CS | C59: 2006 | D59: measures: reasons | E59: multiclass_suitability | F59: Unfortunately, they can hardly be applied to multi-class problems. Therefore, here the misclassification costs are compared. | G59: p. 571, Experiments (cost comparison); p. 571, Experiments (MAUC 'a variant of AUC designed for multi-class class-imbalance learning')
A60: Global-CS-2006 | B60: Global-CS | C60: 2006 | D60: tests: methodology cited | E60: none | G60: p. 571, Experiments, Table 5 (pairwise two-tailed t-tests, 0.05 level; no methodological reference)
A61: Global-CS-2006 | B61: Global-CS | C61: 2006 | D61: beyond classifier scores | E61: theoretical_analysis | Analysis section derives the optimal rescaling ratio and shows traditional rescaling equals it only when c=2; consistency condition stated via rank of the coefficient matrix (Eqs. 3-10) | G61: pp. 568-569, Analysis and The RESCALEnew Approach (Eqs. 1-10, Table 1)
A62: COG-OS-2007 | B62: COG-OS | C62: 2007 | D62: data: reasons | E62: public_benchmark, application_domain, comparability, imbalance_level | F62: For our experiments, we used a number of benchmark data sets that were obtained from different application domains. | G62: p. 817, Sec. 4.1 (Experimental Data Sets); p. 820, Sec. 4.4 (KDD Cup 99 for network intrusion; same source data as [17]); p. 821, Sec. 4.5 (balanced sets with CV < 0.5)
A63: COG-OS-2007 | B63: COG-OS | C63: 2007 | D63: data: access | E63: all public=True; source per dataset=True; links=True; modified data released=False | G63: p. 818, Table 2 (Source column); p. 820, Table 8; p. 823, Refs. [3]-[5], [30] (URLs)
A64: COG-OS-2007 | B64: COG-OS | C64: 2007 | D64: learners: reasons | E64: simplicity, matches_mechanism, other | F64: linear classifiers have various merits such as simplicity and understandability, higher executive efficiency, less parameters, less generalization errors | G64: p. 815, Sec. 2.1; p. 818, Sec. 4.2
A65: COG-OS-2007 | B65: COG-OS | C65: 2007 | D65: model selection | E65: selected: none (fixed settings), method parameters | criterion: Accuracy | data: evaluation data | F65: we first select the highest accuracy among four values achieved in different “#clusters” levels, then subtract it by the accuracy obtained by the pure classifier. | G65: p. 818, Sec. 4.2 (K=4, replication to balance); p. 822, Sec. 4.5, Fig. 6 (maximal accuracy gain)
A66: COG-OS-2007 | B66: COG-OS | C66: 2007 | D66: measures: reasons | E66: none stated
A67: COG-OS-2007 | B67: COG-OS | C67: 2007 | D67: tests: methodology cited | E67: none
A68: COG-OS-2007 | B68: COG-OS | C68: 2007 | D68: beyond classifier scores | E68: toy_2d_visualization, complexity_analysis | Figs. 2-3 plot 2-D synthetic data with linear-SVM hyperplanes for pure SVM, COG, OS and COG-OS; Sec. 2.2 gives an informal linear-time cost argument for the local clustering step. | G68: p. 816, Secs. 2.2-3, Figs. 2-3
A69: COG-OS-2007 | B69: COG-OS | C69: 2007 | D69: settings chosen on evaluation data | E69: explicit | F69: we first select the highest accuracy among four values achieved in different “#clusters” levels, then subtract it by the accuracy obtained by the pure classifier. | G69: p. 818, Sec. 4.2 (K=4, replication to balance); p. 822, Sec. 4.5, Fig. 6 (maximal accuracy gain)
A70: ADASYN-2008 | B70: ADASYN | C70: 2008 | D70: data: reasons | E70: follows_prior_work | F70: we made modifications on several of the original data sets according to various literary results from similar experiments [17] [29] | G70: p. 1324, Sec. III-A; p. 1325 (Abalone 'as suggested in [17]')
A71: ADASYN-2008 | B71: ADASYN | C71: 2008 | D71: data: access | E71: all public=True; source per dataset=False; links=True; modified data released=False | G71: p. 1324, Sec. III-A, Table I; p. 1328, ref. [28] (UCI URL)
A72: ADASYN-2008 | B72: ADASYN | C72: 2008 | D72: learners: reasons | E72: none stated
A73: ADASYN-2008 | B73: ADASYN | C73: 2008 | D73: model selection | E73: selected: none (fixed settings) | criterion: not applicable | data: not applicable | F73: Other parameters include N = 200 for SMOTE according to [15], β = 1 and dth = 0.75 for ADASYN. | G73: p. 1325, Sec. III-C
A74: ADASYN-2008 | B74: ADASYN | C74: 2008 | D74: measures: reasons | E74: accuracy_misleading | F74: We use ROC based evaluation metrics because under the imbalanced learning condition, traditional overall classification accuracy may not be able to provide a comprehensive assessment of the observed learning algorithm | G74: p. 1325, Sec. III-B
A75: ADASYN-2008 | B75: ADASYN | C75: 2008 | D75: tests: methodology cited | E75: none
A76: ADASYN-2008 | B76: ADASYN | C76: 2008 | D76: beyond classifier scores | E76: none
A77: LS-2008 | B77: LS | C77: 2008 | D77: data: reasons | E77: follows_prior_work | F77: Several datasets were acquired from various real-world scenarios originally considered in [6]. | G77: p. 7, Sec. 5.3
A78: LS-2008 | B78: LS | C78: 2008 | D78: data: access | E78: all public=None; source per dataset=True; links=False; modified data released=False | G78: pp. 7-8, Sec. 5.3, Table 2
A79: LS-2008 | B79: LS | C79: 2008 | D79: learners: reasons | E79: popular, simplicity | F79: we restrict our experiments with Undersample/SMOTE and LS with C4.5, which is also the most commonly used classifier with sampling for imbalanced datasets in the literature. | G79: p. 7, Sec. 5.2
A80: LS-2008 | B80: LS | C80: 2008 | D80: model selection | E80: selected: method parameters, sampling rate | criterion: AUC | data: inner validation (training data only) | F80: this 5-fold cv is applied to each of the training sets of 5x2, making it an independent validation framework. | G80: p. 5, Sec. 4; p. 7, Sec. 5.2
A81: LS-2008 | B81: LS | C81: 2008 | D81: measures: reasons | E81: accuracy_misleading, standard_in_literature | F81: Traditional objective metrics, such as accuracy, often fail to describe performance properly under these circumstances as a trivial classifier may produce high accuracy | G81: p. 1, Sec. 1
A82: LS-2008 | B82: LS | C82: 2008 | D82: tests: methodology cited | E82: Dietterich 1998; Alpaydin 1999; Demsar 2006 | G82: pp. 6-7, Sec. 5.1; p. 8, Table 3
A83: LS-2008 | B83: LS | C83: 2008 | D83: beyond classifier scores | E83: toy_2d_visualization | Fig. 4 plots Pima on two attributes showing Hellinger partitions, removed majority points and injected SMOTE points for local vs global sampling | G83: p. 6, Fig. 4
A84: EasyEnsemble-BalanceCascade-2009 | B84: EasyEnsemble | C84: 2009 | D84: data: reasons | E84: none stated
A85: EasyEnsemble-BalanceCascade-2009 | B85: EasyEnsemble | C85: 2009 | D85: data: access | E85: all public=True; source per dataset=False; links=False; modified data released=False | G85: p. 542, Sec. IV-B and Table II caption; ref. [3]
A86: EasyEnsemble-BalanceCascade-2009 | B86: EasyEnsemble | C86: 2009 | D86: learners: reasons | E86: none stated
A87: EasyEnsemble-BalanceCascade-2009 | B87: EasyEnsemble | C87: 2009 | D87: model selection | E87: selected: none (fixed settings) | criterion: not applicable | data: not applicable | F87: CART is used to train weak classifiers. Number of subsets T = 4; number of rounds in each AdaBoost ensemble si = 10. | G87: p. 543, Sec. IV-B (items 10-11)
A88: EasyEnsemble-BalanceCascade-2009 | B88: EasyEnsemble | C88: 2009 | D88: measures: reasons | E88: accuracy_misleading, threshold_free | F88: It is now well known that error rate is not an appropriate evaluation criterion when there are class imbalance or unequal costs. | G88: p. 542, Sec. IV-A
A89: EasyEnsemble-BalanceCascade-2009 | B89: EasyEnsemble | C89: 2009 | D89: tests: methodology cited | E89: none | G89: p. 544, Sec. IV-D; Tables VI, IX, XII (pairwise t-test, significance level 0.05)
A90: EasyEnsemble-BalanceCascade-2009 | B90: EasyEnsemble | C90: 2009 | D90: beyond classifier scores | E90: complexity_analysis | Sec. IV-C analyses training cost of each method from the number of training examples it uses (e.g., Under 2|P|, Over 2|N|); Sec. IV-D derives T = 20 for a face-detection example from log2 of the class ratio. No big-O notation; runtimes in Table III | G90: pp. 543-544, Sec. IV-C; p. 548, Sec. IV-D
A91: SBC-2009 | B91: SBC | C91: 2009 | D91: data: reasons | E91: difficulty_factors | F91: In order to make the synthetic datasets more like real datasets, the noisy data are necessary. | G91: p. 5721, Sec. 4.1
A92: SBC-2009 | B92: SBC | C92: 2009 | D92: data: access | E92: all public=False; source per dataset=True; links=False; modified data released=False | G92: pp. 5725-5726, Sec. 4.4
A93: SBC-2009 | B93: SBC | C93: 2009 | D93: learners: reasons | E93: none stated
A94: SBC-2009 | B94: SBC | C94: 2009 | D94: model selection | E94: selected: none (fixed settings) | criterion: not applicable | data: not applicable | F94: The dataset DSi means that the dataset potentially can be separated into i clusters, and our methods also cluster the dataset DSi into i clusters. | G94: p. 5723, Sec. 4.3
A95: SBC-2009 | B95: SBC | C95: 2009 | D95: measures: reasons | E95: minority_focus, other | F95: We cannot use one of the two criteria to evaluate the performance of a classifier. Hence, the precision rate and recall rate are combined to form another criterion F-measure | G95: pp. 5721-5722, Sec. 4.2
A96: SBC-2009 | B96: SBC | C96: 2009 | D96: tests: methodology cited | E96: none
A97: SBC-2009 | B97: SBC | C97: 2009 | D97: beyond classifier scores | E97: none | Only minority/majority precision, recall and F-measure plus execution time are reported. Figs. 1-3 illustrate the synthetic data generator (clusters, disordered and exceptional samples), not resampled data. | G97: pp. 5721-5726, Figs. 1-12, Table 4
A98: Safe-Level-SMOTE-2009 | B98: Safe-Level-SMOTE | C98: 2009 | D98: data: reasons | E98: none stated
A99: Safe-Level-SMOTE-2009 | B99: Safe-Level-SMOTE | C99: 2009 | D99: data: access | E99: all public=True; source per dataset=True; links=True; modified data released=False | G99: p. 480, Sec. 4 and Table 3; ref. [1] (UCI URL)
A100: Safe-Level-SMOTE-2009 | B100: Safe-Level-SMOTE | C100: 2009 | D100: learners: reasons | E100: none stated
...

Sheet citations
A1: key | B1: study | C1: year | D1: OpenAlex ID | E1: DOI | F1: citations | G1: per year | H1: match | I1: eligible for ratios | J1: note
A2: ENN-1972 | B2: Wilson ENN | C2: 1972 | D2: W2107686700 | E2: 10.1109/tsmc.1972.4309137 | F2: 2133 | G2: =IF(F2="","",ROUND(F2/(2026-C2+1),1)) -> 38.8 | H2: exact | I2: no
A3: TomekLinks-1976 | B3: Tomek links | C3: 1976 | D3: W1591261915 | E3: 10.1109/tsmc.1976.4309452 | F3: 1288 | G3: =IF(F3="","",ROUND(F3/(2026-C3+1),1)) -> 25.3 | H3: exact | I3: no | J3: Re-verified 2026-10-18 via batch filter=openalex:...; count unchanged.
A4: AdaBoost-1997 | B4: AdaBoost | C4: 1997 | D4: W1988790447 | E4: 10.1006/jcss.1997.1504 | F4: 20446 | G4: =IF(F4="","",ROUND(F4/(2026-C4+1),1)) -> 681.5 | H4: exact | I4: no | J4: JCSS journal version chosen. Alt is the EuroCOLT 1995 conference version (10.1007/3-540-59119-2_166; title misspelled in OpenAlex). Re-verified by batch filter=openalex call on 2026-10-18: count unchanged.
A5: OSS-1997 | B5: OSS | C5: 1997 | D5: W85350352 | F5: 2562 | G5: =IF(F5="","",ROUND(F5/(2026-C5+1),1)) -> 85.4 | H5: exact | I5: yes | J5: OpenAlex splits this paper over two records (one with a misspelled title); the two counts are added.
A6: SHRINK-1998 | B6: SHRINK | C6: 1998 | D6: W1588282782 | E6: 10.1023/a:1007452223027 | F6: 1243 | G6: =IF(F6="","",ROUND(F6/(2026-C6+1),1)) -> 42.9 | H6: exact | I6: yes | J6: Full-title search was refused (HTTP 429); found with fallback query (short title + Kubat). Re-verified by batch filter=openalex call on 2026-10-18: count unchanged.
A7: SMOTE-2002 | B7: SMOTE | C7: 2002 | D7: W2148143831 | E7: 10.1613/jair.953 | F7: 32518 | G7: =IF(F7="","",ROUND(F7/(2026-C7+1),1)) -> 1300.7 | H7: exact | I7: yes
A8: SMOTEBoost-2003 | B8: SMOTEBoost | C8: 2003 | D8: W1563938718 | E8: 10.1007/978-3-540-39804-2_12 | F8: 1738 | G8: =IF(F8="","",ROUND(F8/(2026-C8+1),1)) -> 72.4 | H8: exact | I8: yes | J8: Re-verified 2026-10-18 via batch filter=openalex:...; count unchanged.
A9: SMOTE-ENN-Tomek-2004 | B9: Batista et al. | C9: 2004 | D9: W1993220166 | E9: 10.1145/1007730.1007735 | F9: 4207 | G9: =IF(F9="","",ROUND(F9/(2026-C9+1),1)) -> 182.9 | H9: exact | I9: yes
A10: Borderline-SMOTE-2005 | B10: Borderline-SMOTE | C10: 2005 | D10: W2132791018 | E10: 10.1007/11538059_91 | F10: 4313 | G10: =IF(F10="","",ROUND(F10/(2026-C10+1),1)) -> 196 | H10: exact | I10: yes | J10: Re-verified by batch filter=openalex call on 2026-10-18: count unchanged.
A11: Cluster-SMOTE-2006 | B11: Cluster-SMOTE | C11: 2006 | D11: W2126996952 | E11: 10.1109/grc.2006.1635905 | F11: 303 | G11: =IF(F11="","",ROUND(F11/(2026-C11+1),1)) -> 14.4 | H11: exact | I11: yes | J11: IEEE GrC 2006 (input venue was null). Re-verified 2026-10-18 via batch filter=openalex:...; count unchanged.
A12: Global-CS-2006 | B12: Global-CS | C12: 2006 | G12: =IF(F12="","",ROUND(F12/(2026-C12+1),1)) | H12: uncertain | I12: no | J12: The AAAI 2006 paper has no OpenAlex record; the only match is the 2010 journal version, which is a separate corpus entry. Excluded from citation analysis.
A13: COG-OS-2007 | B13: COG-OS | C13: 2007 | D13: W2151779862 | E13: 10.1145/1281192.1281279 | F13: 67 | G13: =IF(F13="","",ROUND(F13/(2026-C13+1),1)) -> 3.4 | H13: exact | I13: yes | J13: KDD 2007 version chosen to match venue; alt is the extended journal version (Data Min. Knowl. Discov. 2010, DOI 10.1007/s10618-009-0146-1) with a slightly different title.
A14: ADASYN-2008 | B14: ADASYN | C14: 2008 | D14: W2104933073 | E14: 10.1109/ijcnn.2008.4633969 | F14: 4927 | G14: =IF(F14="","",ROUND(F14/(2026-C14+1),1)) -> 259.3 | H14: exact | I14: yes | J14: Full-title search was refused (HTTP 429) and the shorter fallback search did not surface it; found via filter=title.search:ADASYN, year 2007-2009 (only 1 hit). Re-verified 2026-10-18 via batch filter=openalex:...; count unchanged.
A15: LS-2008 | B15: LS | C15: 2008 | D15: W2117689108 | E15: 10.1109/icdm.2008.87 | F15: 75 | G15: =IF(F15="","",ROUND(F15/(2026-C15+1),1)) -> 3.9 | H15: exact | I15: yes | J15: Full-title search was refused (HTTP 429) and the fallback search (title words + Cieslak) returned no match; found with filter=title.search. Re-verified by batch filter=openalex call on 2026-10-18: count unchanged.
A16: EasyEnsemble-BalanceCascade-2009 | B16: EasyEnsemble | C16: 2009 | D16: W2104167780 | E16: 10.1109/tsmcb.2008.2007853 | F16: 2475 | G16: =IF(F16="","",ROUND(F16/(2026-C16+1),1)) -> 137.5 | H16: exact | I16: yes | J16: OpenAlex year 2008 (online-first) vs input 2009 (print issue). Re-verified 2026-10-18 via batch filter=openalex:...; count unchanged.
A17: SBC-2009 | B17: SBC | C17: 2009 | D17: W2128965734 | E17: 10.1016/j.eswa.2008.06.108 | F17: 732 | G17: =IF(F17="","",ROUND(F17/(2026-C17+1),1)) -> 40.7 | H17: exact | I17: yes | J17: Full-title search was refused (HTTP 429) and the fallback search (title + Yen) returned no match; resolved by DOI lookup (works/doi:...), title matches exactly. OpenAlex year 2008 (online first), print 2009. Re-verified by batch filter=openalex call on 2026-10-18: count unchanged.
A18: Safe-Level-SMOTE-2009 | B18: Safe-Level-SMOTE | C18: 2009 | D18: W1496056137 | E18: 10.1007/978-3-642-01307-2_43 | F18: 1023 | G18: =IF(F18="","",ROUND(F18/(2026-C18+1),1)) -> 56.8 | H18: exact | I18: yes | J18: Found via shortened title query (full-title query returned a fetch error).
A19: Global-CS-2010 | B19: Global-CS | C19: 2010 | D19: W72187777 | E19: 10.1111/j.1467-8640.2010.00358.x | F19: 350 | G19: =IF(F19="","",ROUND(F19/(2026-C19+1),1)) -> 20.6 | H19: exact | I19: yes | J19: Computational Intelligence journal version. The AAAI 2006 conference paper of the same title did not appear in the top 5 and was not looked up separately. Re-verified 2026-10-18 via batch filter=openalex:...; count unchanged.
A20: RAMOBoost-2010 | B20: RAMOBoost | C20: 2010 | D20: W2096235960 | E20: 10.1109/tnn.2010.2066988 | F20: 208 | G20: =IF(F20="","",ROUND(F20/(2026-C20+1),1)) -> 12.2 | H20: exact | I20: yes
A21: RUSBoost-2010 | B21: RUSBoost | C21: 2010 | D21: W2096945460 | E21: 10.1109/tsmca.2009.2029559 | F21: 1867 | G21: =IF(F21="","",ROUND(F21/(2026-C21+1),1)) -> 109.8 | H21: exact | I21: yes | J21: OpenAlex year 2009 (online-first) vs input 2010 (print issue). The 2008 ICPR precursor has a different title and was not looked up. Re-verified 2026-10-18 via batch filter=openalex:...; count unchanged.
A22: SPIDER2-2010 | B22: SPIDER2 | C22: 2010 | D22: W1592804209 | E22: 10.1007/978-3-642-13529-3_18 | F22: 229 | G22: =IF(F22="","",ROUND(F22/(2026-C22+1),1)) -> 13.5 | H22: exact | I22: yes | J22: Re-verified by batch filter=openalex call on 2026-10-18: count unchanged.
A23: DSRBF-2011 | B23: DSRBF | C23: 2011 | D23: W2124710650 | E23: 10.1016/j.patcog.2011.02.019 | F23: 152 | G23: =IF(F23="","",ROUND(F23/(2026-C23+1),1)) -> 9.5 | H23: exact | I23: yes
A24: INOS-2013 | B24: INOS | C24: 2013 | D24: W2015681982 | E24: 10.1109/tkde.2013.37 | F24: 129 | G24: =IF(F24="","",ROUND(F24/(2026-C24+1),1)) -> 9.2 | H24: exact | I24: yes | J24: Re-verified by batch filter=openalex call on 2026-10-18: count unchanged.
A25: OVO-SMOTE-2013 | B25: Fernandez et al. | C25: 2013 | D25: W2164341120 | E25: 10.1016/j.knosys.2013.01.018 | F25: 388 | G25: =IF(F25="","",ROUND(F25/(2026-C25+1),1)) -> 27.7 | H25: exact | I25: yes | J25: Full-title search URL was too long; the shortened search was refused (HTTP 429); resolved by DOI lookup (works/doi:...), title matches exactly. Re-verified by batch filter=openalex call on 2026-10-18: count unchanged.
A26: MWMOTE-2014 | B26: MWMOTE | C26: 2014 | D26: W2087240369 | E26: 10.1109/tkde.2012.232 | F26: 1153 | G26: =IF(F26="","",ROUND(F26/(2026-C26+1),1)) -> 88.7 | H26: close | I26: yes | J26: Same paper (IEEE TKDE DOI tkde.2012.232); OpenAlex year 2012 is the early-access date, print issue is TKDE 26(2), 2014, so the year differs by 2 from input.
A27: RACOG-2015 | B27: RACOG | C27: 2015 | D27: W2076272581 | E27: 10.1109/tkde.2014.2324567 | F27: 124 | G27: =IF(F27="","",ROUND(F27/(2026-C27+1),1)) -> 10.3 | H27: exact | I27: yes | J27: Full-title and fallback searches were refused (HTTP 429); found via filter=title.search:wRACOG. OpenAlex year 2014 (online-first) vs input 2015. Alt is the ICDM 2013 precursor (different title, DOI 10.1109/icdm.2013.18), listed for reference only. Re-verified 2026-10-18 via batch filter=openalex:...
A28: RBBoost-2015 | B28: Random Balance | C28: 2015 | D28: W769353746 | E28: 10.1016/j.knosys.2015.04.022 | F28: 235 | G28: =IF(F28="","",ROUND(F28/(2026-C28+1),1)) -> 19.6 | H28: exact | I28: yes | J28: Re-verified by batch filter=openalex call on 2026-10-18: count unchanged.
A29: SCUT-2015 | B29: SCUT | C29: 2015 | D29: W2294246171 | E29: 10.5220/0005595502260234 | F29: 105 | G29: =IF(F29="","",ROUND(F29/(2026-C29+1),1)) -> 8.8 | H29: exact | I29: yes | J29: SCITEPRESS DOI (KDIR 2015); input venue was null. Re-verified 2026-10-18 via batch filter=openalex:...; count unchanged.
A30: SMOTE-IPF-2015 | B30: SMOTE-IPF | C30: 2015 | D30: W2107138773 | E30: 10.1016/j.ins.2014.08.051 | F30: 627 | G30: =IF(F30="","",ROUND(F30/(2026-C30+1),1)) -> 52.3 | H30: exact | I30: yes | J30: OpenAlex year 2014 (online first); Information Sciences 291 (2015). A separate precursor paper (IDEAL 2014, 'Managing Borderline and Noisy Examples ... SMOTE with Ensemble Filtering', W10885063, 25 cites) is a different work, not listed as a version.
A31: SplitBal-2015 | B31: SplitBal | C31: 2015 | D31: W2091007025 | E31: 10.1016/j.patcog.2014.11.014 | F31: 414 | G31: =IF(F31="","",ROUND(F31/(2026-C31+1),1)) -> 34.5 | H31: exact | I31: yes | J31: OpenAlex year 2014 (online-first) vs input 2015; Pattern Recognition DOI. Re-verified 2026-10-18 via batch filter=openalex:...; count unchanged.
A32: A-SUWO-2016 | B32: A-SUWO | C32: 2016 | D32: W2172165257 | F32: 291 | G32: =IF(F32="","",ROUND(F32/(2026-C32+1),1)) -> 26.5 | H32: exact | I32: yes | J32: The PDF in the corpus is the dissertation chapter (0 citations in OpenAlex); the method is cited through its Expert Systems with Applications article, which is used.
A33: CGMOS-2016 | B33: CGMOS | C33: 2016 | D33: W2476542064 | E33: 10.1145/2983323.2983789 | F33: 25 | G33: =IF(F33="","",ROUND(F33/(2026-C33+1),1)) -> 2.3 | H33: close | I33: yes | J33: CIKM 2016 version chosen (ACM DOI); OpenAlex display_name is truncated to 'CGMOS'. arXiv 1607.06525 preprint listed as alt. Re-verified 2026-10-18 via batch filter=openalex:...; count unchanged.
A34: MDO-2016 | B34: MDO | C34: 2016 | D34: W2185967890 | E34: 10.1109/tkde.2015.2458858 | F34: 411 | G34: =IF(F34="","",ROUND(F34/(2026-C34+1),1)) -> 37.4 | H34: exact | I34: yes | J34: OpenAlex year 2015 (early access); IEEE TKDE 28(1), 2016. A different 2014 paper by the same authors (Soft Computing, '...over-sampling and boosting techniques', W2027347092, 45 cites) is not a version.
A35: SMOM-2017 | B35: SMOM | C35: 2017 | D35: W2736435690 | E35: 10.1016/j.patcog.2017.07.024 | F35: 277 | G35: =IF(F35="","",ROUND(F35/(2026-C35+1),1)) -> 27.7 | H35: exact | I35: yes | J35: Full-title search was refused (HTTP 429) and the fallback search missed it; found via filter=title.search:multiclass imbalance problems, year 2017 (only 1 hit). Re-verified 2026-10-18 via batch filter=openalex:...; count unchanged.
A36: AMDO-2018 | B36: AMDO | C36: 2018 | D36: W2763110968 | E36: 10.1109/tkde.2017.2761347 | F36: 80 | G36: =IF(F36="","",ROUND(F36/(2026-C36+1),1)) -> 8.9 | H36: exact | I36: yes | J36: OpenAlex year 2017 (early access), issue 2018. Re-verified by batch filter=openalex call on 2026-10-18: count unchanged.
A37: KMeansSMOTE-2018 | B37: k-means SMOTE | C37: 2018 | D37: W2766296277 | E37: 10.1016/j.ins.2018.06.056 | F37: 1273 | G37: =IF(F37="","",ROUND(F37/(2026-C37+1),1)) -> 141.4 | H37: exact | I37: yes | J37: The 2017 arXiv preprint has a different title and was not looked up. Re-verified 2026-10-18 via batch filter=openalex:...; count unchanged.
A38: OBU-2018 | B38: OBU | C38: 2018 | D38: W2900321945 | E38: 10.1007/978-3-030-03493-1_72 | F38: 71 | G38: =IF(F38="","",ROUND(F38/(2026-C38+1),1)) -> 7.9 | H38: exact | I38: yes | J38: Re-verified by batch filter=openalex call on 2026-10-18: count unchanged.
A39: ROS-Buda-2018 | B39: Buda et al. | C39: 2018 | D39: W2767106145 | E39: 10.1016/j.neunet.2018.07.011 | F39: 3053 | G39: =IF(F39="","",ROUND(F39/(2026-C39+1),1)) -> 339.2 | H39: exact | I39: yes | J39: No separate arXiv version appeared in the top search results. Re-verified by batch filter=openalex call on 2026-10-18: count unchanged.
A40: CTGAN-2019 | B40: CTGAN | C40: 2019 | D40: W2954395498 | E40: 10.48550/arxiv.1907.00503 | F40: 982 | G40: =IF(F40="","",ROUND(F40/(2026-C40+1),1)) -> 122.8 | H40: close | I40: yes | J40: Only the arXiv preprint record exists in OpenAlex; no separate NeurIPS 2019 proceedings record was found (also checked with filter=title.search, years 2019-2020). Count likely understates citations to the NeurIPS version. Re-verified 2026-10-18 via batch filter=openalex:...; count unchanged.
A41: G-SMOTE-2019 | B41: G-SMOTE | C41: 2019 | D41: W2948219206 | E41: 10.1016/j.ins.2019.06.007 | F41: 291 | G41: =IF(F41="","",ROUND(F41/(2026-C41+1),1)) -> 36.4 | H41: exact | I41: yes
A42: GAMO-2019 | B42: GAMO | C42: 2019 | D42: W2924282518 | E42: 10.1109/iccv.2019.00178 | F42: 244 | G42: =IF(F42="","",ROUND(F42/(2026-C42+1),1)) -> 30.5 | H42: exact | I42: yes
A43: RBO-2019 | B43: RBO | C43: 2019 | D43: W2914361121 | E43: 10.1016/j.neucom.2018.04.089 | F43: 148 | G43: =IF(F43="","",ROUND(F43/(2026-C43+1),1)) -> 18.5 | H43: exact | I43: yes | J43: Full-title, fallback and DOI lookups were refused (HTTP 429) or returned no match; found with filter=title.search. Related earlier conference paper with a different title: W2617368871 'Radial-Based Approach to Imbalanced Data Oversampling' (HAIS 2017, 28 cites), not counted as a version. Re-verified
A44: SOUP-2019 | B44: SOUP | C44: 2019 | D44: W2998823736 | E44: 10.2478/amcs-2019-0057 | F44: 51 | G44: =IF(F44="","",ROUND(F44/(2026-C44+1),1)) -> 6.4 | H44: exact | I44: yes
A45: AB-SMOTE-2020 | B45: AB-SMOTE | C45: 2020 | D45: W3015143107 | E45: 10.18178/ijmlc.2020.10.1.894 | F45: 34 | G45: =IF(F45="","",ROUND(F45/(2026-C45+1),1)) -> 4.9 | H45: exact | I45: yes
A46: DLexiBoost-2020 | B46: DLexiBoost | C46: 2020 | D46: W2913816472 | E46: 10.1109/tkde.2019.2894148 | F46: 38 | G46: =IF(F46="","",ROUND(F46/(2026-C46+1),1)) -> 5.4 | H46: exact | I46: yes | J46: OpenAlex year 2019 (online-first) vs input 2020. Re-verified 2026-10-18 via batch filter=openalex:...; count unchanged.
A47: MBS-2020 | B47: MBS | C47: 2020 | D47: W2922054794 | E47: 10.1109/tkde.2019.2905559 | F47: 93 | G47: =IF(F47="","",ROUND(F47/(2026-C47+1),1)) -> 13.3 | H47: exact | I47: yes | J47: Full-title search was refused (HTTP 429); found with filter=title.search. OpenAlex year 2019 (early access), issue 2020. A different work with the same title exists (W4206062307, IJRTE 2020, 10.35940/ijrte.f7545.038620, 3 cites); not this paper. Re-verified by batch filter=openalex call on 2026-10-1
A48: MC-CCR-2020 | B48: MC-CCR | C48: 2020 | D48: W3015358651 | E48: 10.1016/j.knosys.2020.106223 | F48: 166 | G48: =IF(F48="","",ROUND(F48/(2026-C48+1),1)) -> 23.7 | H48: exact | I48: yes | J48: Re-verified 2026-10-18 via batch filter=openalex:...; count unchanged.
A49: MC-RBO-2020 | B49: MC-RBO | C49: 2020 | D49: W2952448206 | E49: 10.1109/tnnls.2019.2913673 | F49: 122 | G49: =IF(F49="","",ROUND(F49/(2026-C49+1),1)) -> 17.4 | H49: exact | I49: yes | J49: OpenAlex year 2019 (early access), issue 2020. Re-verified by batch filter=openalex call on 2026-10-18: count unchanged.
A50: NBU-2020 | B50: NBU | C50: 2020 | D50: W2971749073 | E50: 10.1016/j.ins.2019.08.062 | F50: 286 | G50: =IF(F50="","",ROUND(F50/(2026-C50+1),1)) -> 40.9 | H50: exact | I50: yes | J50: OpenAlex year 2019 (online-first) vs input 2020. Re-verified 2026-10-18 via batch filter=openalex:...; count unchanged.
A51: SPE-2020 | B51: SPE | C51: 2020 | D51: W3031232306 | E51: 10.1109/icde48307.2020.00078 | F51: 233 | G51: =IF(F51="","",ROUND(F51/(2026-C51+1),1)) -> 33.3 | H51: exact | I51: yes
A52: EMDO-2021 | B52: EMDO | C52: 2021 | D52: W3204058295 | E52: 10.3390/s21196616 | F52: 18 | G52: =IF(F52="","",ROUND(F52/(2026-C52+1),1)) -> 3 | H52: exact | I52: yes | J52: Found via retry query (title words + 'Yao') because the full-title query was rate-limited.
A53: HDE-2021 | B53: HDE | C53: 2021 | D53: W3111875476 | E53: 10.1016/j.ins.2020.12.023 | F53: 89 | G53: =IF(F53="","",ROUND(F53/(2026-C53+1),1)) -> 14.8 | H53: exact | I53: yes | J53: OpenAlex year 2020 (online first), issue 2021. Re-verified by batch filter=openalex call on 2026-10-18: count unchanged.
A54: PradiptaReview-2021 | B54: Pradipta et al. | C54: 2021 | D54: W4200494353 | E54: 10.1109/icic54025.2021.9632912 | F54: 166 | G54: =IF(F54="","",ROUND(F54/(2026-C54+1),1)) -> 27.7 | H54: exact | I54: no | J54: IEEE ICIC 2021 proceedings (DOI icic54025.2021).
A55: RSMOTE-2021 | B55: RSMOTE | C55: 2021 | D55: W3093212523 | E55: 10.1016/j.ins.2020.10.013 | F55: 178 | G55: =IF(F55="","",ROUND(F55/(2026-C55+1),1)) -> 29.7 | H55: exact | I55: yes | J55: OpenAlex year 2020 (online first); Information Sciences 553 (2021).
A56: CBHSID-2022 | B56: CBHSID | C56: 2022 | D56: W4313017257 | E56: 10.1109/access.2022.3218463 | F56: 31 | G56: =IF(F56="","",ROUND(F56/(2026-C56+1),1)) -> 6.2 | H56: exact | I56: yes | J56: Re-verified 2026-10-18 via batch filter=openalex:...; count unchanged.
A57: FW-SMOTE-2022 | B57: FW-SMOTE | C57: 2022 | D57: W4200472276 | E57: 10.1016/j.patcog.2021.108511 | F57: 177 | G57: =IF(F57="","",ROUND(F57/(2026-C57+1),1)) -> 35.4 | H57: exact | I57: yes | J57: OpenAlex year 2021 (online first); Pattern Recognition 124 (2022). Found in results of the SVDDWSMOTE query because the FW-SMOTE full-title query was rate-limited.
A58: GDO-2022 | B58: GDO | C58: 2022 | D58: W3015967287 | E58: 10.1109/tkde.2020.2985965 | F58: 143 | G58: =IF(F58="","",ROUND(F58/(2026-C58+1),1)) -> 28.6 | H58: close | I58: yes | J58: Exact title and TKDE DOI, but OpenAlex year 2020 (early access) is 2 years from the input year 2022 (issue year); same paper. Re-verified by batch filter=openalex call on 2026-10-18: count unchanged.
A59: KNNOR-2022 | B59: KNNOR | C59: 2022 | D59: W4200122681 | E59: 10.1016/j.asoc.2021.108288 | F59: 138 | G59: =IF(F59="","",ROUND(F59/(2026-C59+1),1)) -> 27.6 | H59: exact | I59: yes | J59: OpenAlex year 2021 (online-first) vs input 2022. Re-verified 2026-10-18 via batch filter=openalex:...; count unchanged.
A60: SHSampler-2022 | B60: SHSampler | C60: 2022 | D60: W4319778623 | E60: 10.1109/dsaa54385.2022.10032369 | F60: 5 | G60: =IF(F60="","",ROUND(F60/(2026-C60+1),1)) -> 1 | H60: exact | I60: yes | J60: Venue per OpenAlex/DOI: IEEE DSAA 2022 (input venue was null). Full-title search was refused (HTTP 429) and the fallback search returned no match; found with filter=title.search (1 match). Re-verified by batch filter=openalex call on 2026-10-18: count unchanged.
A61: SOS-2022 | B61: SOS | C61: 2022 | D61: W4290876805 | E61: 10.1145/3534678.3539454 | F61: 21 | G61: =IF(F61="","",ROUND(F61/(2026-C61+1),1)) -> 4.2 | H61: close | I61: yes | J61: KDD 2022 version chosen (ACM DOI); OpenAlex display_name is truncated to 'SOS'. arXiv 2206.08555 preprint listed as alt. Re-verified 2026-10-18 via batch filter=openalex:...; count unchanged.
A62: SVDDWSMOTE-2022 | B62: SVDD-WSMOTE | C62: 2022 | D62: W4200464085 | E62: 10.1016/j.ins.2021.12.066 | F62: 70 | G62: =IF(F62="","",ROUND(F62/(2026-C62+1),1)) -> 14 | H62: exact | I62: yes | J62: OpenAlex year 2021 (online first); Information Sciences 2022.
A63: StopOversampling-2022 | B63: Hassanat et al. | C63: 2022 | D63: W4226084339 | E63: 10.21203/rs.3.rs-1336037/v1 | F63: 159 | G63: =IF(F63="","",ROUND(F63/(2026-C63+1),1)) -> 31.8 | H63: exact | I63: no | J63: The published IEEE Access version is used instead of the Research Square preprint.
... A77: QC-SMOTE-2026 | B77: QC-SMOTE | C77: 2026 | D77: W7165798645 | E77: 10.48550/arxiv.2606.24625 | F77: 0 | G77: =IF(F77="","",ROUND(F77/(2026-C77+1),1)) -> 0 | H77: exact | I77: no | J77: Full-title search was refused (HTTP 429); found with filter=title.search (1 match). arXiv id matches the input venue. Re-verified by batch filter=openalex call on 2026-10-18: count unchanged.

Sheet summary
A1: status | B1: rows
A2: verified | B2: =COUNTIF(codes!I:I,A2) -> 0
A3: corrected | B3: =COUNTIF(codes!I:I,A3) -> 0
A4: wrong | B4: =COUNTIF(codes!I:I,A4) -> 0
A5: not yet checked | B5: =COUNTA(codes!A:A)-1-SUM(B2:B4) -> 532
A6: total rows | B6: =COUNTA(codes!A:A)-1 -> 532
